purepress/__init__.py
purepress/__main__.py
purepress/__meta__.py
purepress-0.10.0.dist-info/LICENSE
purepress-0.10.0.dist-info/METADATA
purepress-0.10.0.dist-info/WHEEL
purepress-0.10.0.dist-info/entry_points.txt
purepress-0.10.0.dist-info/RECORD
