Metadata-Version: 2.3
Name: purepress
Version: 0.10.0
Summary: A simple static blog generator.
License: MIT
Keywords: Static Blog Generator,Static Blog,Blog,Blog Engine
Author: Richard Chien
Author-email: richardchienthebest@gmail.com
Requires-Python: >=3.12,<3.14
Classifier: Development Status :: 4 - Beta
Classifier: Framework :: Flask
Classifier: License :: OSI Approved :: MIT License
Classifier: Operating System :: OS Independent
Classifier: Programming Language :: Python :: 3
Classifier: Programming Language :: Python :: 3.12
Classifier: Programming Language :: Python :: 3.13
Classifier: Programming Language :: Python :: 3 :: Only
Requires-Dist: Flask (>=3.1.0,<3.2.0)
Requires-Dist: Markdown (>=3.7,<3.8)
Requires-Dist: MarkupSafe (>=3.0.2,<3.1.0)
Requires-Dist: PyYAML (>=6.0.2,<6.1.0)
Requires-Dist: Werkzeug (>=3.1.3,<3.2.0)
Requires-Dist: click (>=8.1.8,<8.2.0)
Requires-Dist: colorama (>=0.4.6,<0.5.0)
Requires-Dist: feedgen (>=1.0.0,<1.1.0)
Requires-Dist: html-toc (>=0.1.2,<0.2.0)
Requires-Dist: py-gfm (>=2.0.0,<2.1.0)
Requires-Dist: pytz (>=2025.2,<2025.3)
Requires-Dist: toml (>=0.10.2,<0.11.0)
Project-URL: Repository, https://github.com/verilab/purepress
